lite_telegram/__init__.py
lite_telegram/bot.py
lite_telegram/context.py
lite_telegram/exceptions.py
lite_telegram/manager.py
lite_telegram/models.py
lite_telegram/types.py
lite_telegram/utils.py
lite_telegram-0.7.3.dist-info/METADATA
lite_telegram-0.7.3.dist-info/WHEEL
lite_telegram-0.7.3.dist-info/licenses/LICENSE
lite_telegram-0.7.3.dist-info/RECORD
