Metadata-Version: 2.4
Name: lite-telegram
Version: 0.7.3
Summary: Add your description here
Author-email: AndKraev <akrstp@gmail.com>
License-File: LICENSE
Requires-Python: >=3.13
Requires-Dist: croniter>=6.0.0
Requires-Dist: httpx>=0.28.1
Requires-Dist: loguru>=0.7.3
Requires-Dist: pydantic>=2.11.5
Requires-Dist: tenacity>=9.1.2
